{"bytes": [{"date": "2021-01-17", "bytes": 12986373, "cachedBytes": 7802670}, {"date": "2021-01-18", "bytes": 26577877, "cachedBytes": 15617252}, {"date": "2021-01-19", "bytes": 38056554, "cachedBytes": 19295307}, {"date": "2021-01-20", "bytes": 27266330, "cachedBytes": 16090723}, {"date": "2021-01-21", "bytes": 41605496, "cachedBytes": 11161441}, {"date": "2021-01-22", "bytes": 21558509, "cachedBytes": 5355767}], "requests": [{"date": "2021-01-17", "requests": 718, "cachedRequests": 124}, {"date": "2021-01-18", "requests": 1339, "cachedRequests": 219}, {"date": "2021-01-19", "requests": 1523, "cachedRequests": 357}, {"date": "2021-01-20", "requests": 1273, "cachedRequests": 200}, {"date": "2021-01-21", "requests": 2055, "cachedRequests": 393}, {"date": "2021-01-22", "requests": 1268, "cachedRequests": 212}], "views": [{"date": "2021-01-17", "pageViews": 69}, {"date": "2021-01-18", "pageViews": 188}, {"date": "2021-01-19", "pageViews": 143}, {"date": "2021-01-20", "pageViews": 207}, {"date": "2021-01-21", "pageViews": 218}, {"date": "2021-01-22", "pageViews": 208}], "bytes_ratio": [{"date": "2021-01-17", "bytesRatio": 0.6008351985577497}, {"date": "2021-01-18", "bytesRatio": 0.5876034417647429}, {"date": "2021-01-19", "bytesRatio": 0.5070166626226852}, {"date": "2021-01-20", "bytesRatio": 0.5901316018694118}, {"date": "2021-01-21", "bytesRatio": 0.26826842780578797}, {"date": "2021-01-22", "bytesRatio": 0.24842937885917807}], "requests_ratio": [{"date": "2021-01-17", "requestRatio": 0.17270194986072424}, {"date": "2021-01-18", "requestRatio": 0.16355489171023152}, {"date": "2021-01-19", "requestRatio": 0.23440577806959947}, {"date": "2021-01-20", "requestRatio": 0.15710919088766692}, {"date": "2021-01-21", "requestRatio": 0.19124087591240876}, {"date": "2021-01-22", "requestRatio": 0.167192429022082}]}
